calibsunapi/__init__.py
calibsunapi/client.py
calibsunapi/decorators.py
calibsunapi/endpoints.py
calibsunapi/exceptions.py
calibsunapi/token.py
calibsunapi/utils.py
calibsunapi/models/__init__.py
calibsunapi/models/listplants.py
calibsunapi/models/targets.py
calibsunapi/models/uploadmeasurements.py
calibsunapi-0.0.29.dist-info/METADATA
calibsunapi-0.0.29.dist-info/WHEEL
calibsunapi-0.0.29.dist-info/top_level.txt
calibsunapi-0.0.29.dist-info/RECORD
