Metadata-Version: 2.4
Name: calibsunapi
Version: 0.0.29
Summary: Lightweight client to interact with Calibsun's API
Author-email: Calibsun <rpartouche@calibsun.com>
Project-URL: Homepage, https://github.com/SOLAIS-FORECAST/api-python-client
Project-URL: Issues, https://github.com/SOLAIS-FORECAST/api-python-client/issues
Project-URL: Documentation, https://solais-forecast.github.io/api-python-client/
Classifier: Programming Language :: Python :: 3
Classifier: License :: OSI Approved :: MIT License
Classifier: Operating System :: OS Independent
Requires-Python: >=3.8
